enact/__init__.py
enact/acyclic.py
enact/contexts.py
enact/digests.py
enact/distribution_registry.py
enact/function_wrappers.py
enact/interfaces.py
enact/invocation_generators.py
enact/invocations.py
enact/pretty_print.py
enact/py.typed
enact/references.py
enact/registration.py
enact/resource_digests.py
enact/resource_registry.py
enact/resources.py
enact/serialization.py
enact/type_inference.py
enact/type_wrappers.py
enact/types.py
enact/utils.py
enact/version.py
enact/fastapi/__init__.py
enact/fastapi/fastapi.py
enact/gradio/__init__.py
enact/gradio/gradio.py
enact-0.4.14.dist-info/licenses/LICENSE
enact-0.4.14.dist-info/METADATA
enact-0.4.14.dist-info/WHEEL
enact-0.4.14.dist-info/top_level.txt
enact-0.4.14.dist-info/RECORD
