Metadata-Version: 2.4
Name: enact
Version: 0.4.14
Summary: A framework for generative software.
Classifier: Programming Language :: Python :: 3
Classifier: License :: OSI Approved :: Apache Software License
Classifier: Operating System :: OS Independent
Requires-Python: >=3.10
License-File: LICENSE
Requires-Dist: wrapt
Dynamic: license-file
